django_admin_mcp/__init__.py
django_admin_mcp/admin.py
django_admin_mcp/apps.py
django_admin_mcp/mixin.py
django_admin_mcp/models.py
django_admin_mcp/urls.py
django_admin_mcp/views.py
django_admin_mcp/handlers/__init__.py
django_admin_mcp/handlers/actions.py
django_admin_mcp/handlers/base.py
django_admin_mcp/handlers/crud.py
django_admin_mcp/handlers/meta.py
django_admin_mcp/handlers/relations.py
django_admin_mcp/migrations/0001_initial.py
django_admin_mcp/migrations/__init__.py
django_admin_mcp/protocol/__init__.py
django_admin_mcp/protocol/errors.py
django_admin_mcp/protocol/jsonrpc.py
django_admin_mcp/protocol/types.py
django_admin_mcp/tools/__init__.py
django_admin_mcp/tools/registry.py
django_admin_mcp-0.2.1.dist-info/licenses/LICENSE
django_admin_mcp-0.2.1.dist-info/METADATA
django_admin_mcp-0.2.1.dist-info/WHEEL
django_admin_mcp-0.2.1.dist-info/top_level.txt
django_admin_mcp-0.2.1.dist-info/RECORD
