Metadata-Version: 2.4
Name: django-admin-mcp
Version: 0.2.1
Summary: Django admin MCP integration - expose Django admin models to MCP clients
Home-page: https://github.com/7tg/django-admin-mcp
Author: Barbaros Goren
Author-email: Barbaros Goren <gorenbarbaros@gmail.com>
Maintainer-email: Barbaros Goren <gorenbarbaros@gmail.com>
License-Expression: GPL-3.0-or-later
Project-URL: Homepage, https://github.com/7tg/django-admin-mcp
Project-URL: Documentation, https://7tg.github.io/django-admin-mcp/
Project-URL: Repository, https://github.com/7tg/django-admin-mcp
Project-URL: Issues, https://github.com/7tg/django-admin-mcp/issues
Project-URL: Changelog, https://github.com/7tg/django-admin-mcp/releases
Keywords: django,admin,mcp,model-context-protocol,llm,ai,automation,api
Classifier: Development Status :: 3 - Alpha
Classifier: Intended Audience :: Developers
Classifier: Framework :: Django
Classifier: Framework :: Django :: 3.2
Classifier: Framework :: Django :: 4.0
Classifier: Framework :: Django :: 4.1
Classifier: Framework :: Django :: 4.2
Classifier: Framework :: Django :: 5.0
Classifier: Operating System :: OS Independent
Classifier: Programming Language :: Python :: 3
Classifier: Programming Language :: Python :: 3.10
Classifier: Programming Language :: Python :: 3.11
Classifier: Programming Language :: Python :: 3.12
Classifier: Programming Language :: Python :: 3 :: Only
Classifier: Topic :: Software Development :: Libraries :: Python Modules
Classifier: Topic :: Internet :: WWW/HTTP
Classifier: Topic :: Internet :: WWW/HTTP :: Dynamic Content
Requires-Python: >=3.10
License-File: LICENSE
Requires-Dist: django>=3.2
Requires-Dist: pydantic>=2.0
Provides-Extra: dev
Requires-Dist: pytest>=7.0; extra == "dev"
Requires-Dist: pytest-django>=4.5; extra == "dev"
Requires-Dist: pytest-asyncio>=0.21.0; extra == "dev"
Requires-Dist: pytest-cov>=4.0; extra == "dev"
Requires-Dist: factory-boy>=3.3.0; extra == "dev"
Requires-Dist: pytest-factoryboy>=2.5.0; extra == "dev"
Requires-Dist: ruff>=0.4.0; extra == "dev"
Requires-Dist: mypy>=1.10.0; extra == "dev"
Requires-Dist: django-stubs>=5.0.0; extra == "dev"
Requires-Dist: pre-commit>=3.7.0; extra == "dev"
Requires-Dist: djlint>=1.34.0; extra == "dev"
Provides-Extra: docs
Requires-Dist: mkdocs>=1.6; extra == "docs"
Requires-Dist: mkdocs-material>=9.5; extra == "docs"
Dynamic: author
Dynamic: home-page
Dynamic: license-file
Dynamic: requires-python
